{
  "$schema": "https://developer.microsoft.com/json-schemas/spfx-build/package-solution.schema.json",
  "solution": {
    "name": "team-sites-web-part-client-side-solution",
    "id": "8c783fa4-bd36-430d-a383-e294e6881ed4",
    "version": "1.0.0.0",
    "includeClientSideAssets": true,
    "skipFeatureDeployment": true,
    "isDomainIsolated": false,
    "developer": {
      "name": "CARD",
      "websiteUrl": "https://www.yourcompany.com",
      "privacyUrl": "https://www.yourcompany.com/privacy",
      "termsOfUseUrl": "https://www.yourcompany.com/terms",
      "mpnId": "Undefined-1.18.2"
    },
    "metadata": {
      "shortDescription": {
        "default": "Displays all Microsoft 365 team sites the user is a member of."
      },
      "longDescription": {
        "default": "An SPFx web part that dynamically shows all Microsoft 365 team sites the logged-in user is a member of, using Microsoft Graph API."
      },
      "screenshotPaths": [],
      "videoUrl": "",
      "categories": ["Collaboration", "Productivity"]
    },
    "features": [
      {
        "title": "team-sites-web-part Feature",
        "description": "The feature that activates elements of the team-sites-web-part solution.",
        "id": "612e0975-2d83-4236-b88b-743efcbc1dee",
        "version": "1.0.0.0"
      }
    ],
    "webApiPermissionRequests": [
      {
        "resource": "Microsoft Graph",
        "scope": "Group.Read.All"
      },
      {
        "resource": "Microsoft Graph",
        "scope": "Sites.Read.All"
      }
    ]
  },
  "paths": {
    "zippedPackage": "solution/team-sites-web-part.sppkg"
  }
}
